{
  "magnito": "evidence-bundle",
  "version": "1.0",
  "timestamp": "2026-04-09T08:58:25.028Z",
  "bridgeCycle": {
    "invoiceId": "3",
    "ethereumContract": "0xBC43a77DB72ffecD94f1D222357f433ba3fE8086",
    "documentHash": "QmMagnitoBridgeTest005",
    "seller": "0x4584b1090382714Be4763Dc965Ae4B30549fDD95",
    "amount": "10000"
  },
  "events": {
    "lock": {
      "action": "invoice-locked",
      "chain": "ethereum-sepolia",
      "txHash": "0x7463441f1c2a4ffb67f9d7ba8a82c8245ce790c4b482e585f31228f8f0568a1f",
      "timestamp": "2026-04-09T08:58:01.009Z"
    },
    "mint": {
      "action": "xrpl-minted",
      "chain": "xrpl-testnet",
      "txHash": "0B6C21A054E54905DEB0B4DDFD7AE225B968767AABDAC1D24F291433BB7FA503",
      "timestamp": "2026-04-09T08:58:05.790Z"
    },
    "return": {
      "action": "xrpl-return-recorded",
      "chain": "xrpl-testnet",
      "txHash": "267094D35358424327E572B59733DF0566FB07874E4176F80E235F0309A25DA4",
      "timestamp": "2026-04-09T08:58:11.278Z"
    },
    "unlock": {
      "action": "invoice-unlocked",
      "chain": "ethereum-sepolia",
      "txHash": "0x3c106dbeb83c52b249b74a8fdaaa9fcf8d4b2c3638410dd6742139481873f507",
      "timestamp": "2026-04-09T08:58:24.984Z"
    }
  },
  "compliance": {
    "mletr": {
      "singularity": "enforced — only one chain authoritative at any time",
      "control": "enforced — seller key required for lock and unlock",
      "integrity": "enforced — documentHash recorded at every stage"
    },
    "bridgeProtocol": "2-phase commit"
  },
  "status": "complete"
}